whisper_timestamped/__init__.py
whisper_timestamped/make_subtitles.py
whisper_timestamped/transcribe.py
whisper_timestamped-1.15.9.dist-info/licenses/LICENSE
whisper_timestamped-1.15.9.dist-info/METADATA
whisper_timestamped-1.15.9.dist-info/WHEEL
whisper_timestamped-1.15.9.dist-info/entry_points.txt
whisper_timestamped-1.15.9.dist-info/top_level.txt
whisper_timestamped-1.15.9.dist-info/RECORD
